nerfstudio/__init__.py
nerfstudio/py.typed
nerfstudio/cameras/__init__.py
nerfstudio/cameras/camera_optimizers.py
nerfstudio/cameras/camera_paths.py
nerfstudio/cameras/camera_utils.py
nerfstudio/cameras/cameras.py
nerfstudio/cameras/lie_groups.py
nerfstudio/cameras/rays.py
nerfstudio/configs/__init__.py
nerfstudio/configs/base_config.py
nerfstudio/configs/config_utils.py
nerfstudio/configs/dataparser_configs.py
nerfstudio/configs/experiment_config.py
nerfstudio/configs/external_methods.py
nerfstudio/configs/method_configs.py
nerfstudio/data/__init__.py
nerfstudio/data/pixel_samplers.py
nerfstudio/data/scene_box.py
nerfstudio/data/datamanagers/__init__.py
nerfstudio/data/datamanagers/base_datamanager.py
nerfstudio/data/datamanagers/full_images_datamanager.py
nerfstudio/data/datamanagers/parallel_datamanager.py
nerfstudio/data/datamanagers/random_cameras_datamanager.py
nerfstudio/data/dataparsers/__init__.py
nerfstudio/data/dataparsers/arkitscenes_dataparser.py
nerfstudio/data/dataparsers/base_dataparser.py
nerfstudio/data/dataparsers/blender_dataparser.py
nerfstudio/data/dataparsers/colmap_dataparser.py
nerfstudio/data/dataparsers/dnerf_dataparser.py
nerfstudio/data/dataparsers/dycheck_dataparser.py
nerfstudio/data/dataparsers/instant_ngp_dataparser.py
nerfstudio/data/dataparsers/minimal_dataparser.py
nerfstudio/data/dataparsers/nerfosr_dataparser.py
nerfstudio/data/dataparsers/nerfstudio_dataparser.py
nerfstudio/data/dataparsers/nuscenes_dataparser.py
nerfstudio/data/dataparsers/phototourism_dataparser.py
nerfstudio/data/dataparsers/scannet_dataparser.py
nerfstudio/data/dataparsers/scannetpp_dataparser.py
nerfstudio/data/dataparsers/sdfstudio_dataparser.py
nerfstudio/data/dataparsers/sitcoms3d_dataparser.py
nerfstudio/data/datasets/__init__.py
nerfstudio/data/datasets/base_dataset.py
nerfstudio/data/datasets/depth_dataset.py
nerfstudio/data/datasets/sdf_dataset.py
nerfstudio/data/datasets/semantic_dataset.py
nerfstudio/data/utils/__init__.py
nerfstudio-1.1.5.dist-info/LICENSE
nerfstudio-1.1.5.dist-info/METADATA
nerfstudio-1.1.5.dist-info/WHEEL
nerfstudio-1.1.5.dist-info/entry_points.txt
nerfstudio-1.1.5.dist-info/top_level.txt
nerfstudio-1.1.5.dist-info/RECORD
